xchem_db/__init__.py
xchem_db/admin.py
xchem_db/models.py
xchem_db/settings.py
xchem_db/urls.py
xchem_db/wsgi.py
xchem_db/migrations/0001_initial.py
xchem_db/migrations/0002_reviewresponses_comment.py
xchem_db/migrations/__init__.py
xcdb-0.4.2b0.dist-info/METADATA
xcdb-0.4.2b0.dist-info/WHEEL
xcdb-0.4.2b0.dist-info/entry_points.txt
xcdb-0.4.2b0.dist-info/top_level.txt
xcdb-0.4.2b0.dist-info/RECORD
