Metadata-Version: 2.1
Name: xcdb
Version: 0.4.2b0
Summary: Library for XChem Django database
Home-page: https://github.com/xchem/xchem_db.git
Author: Rachael Skyner
Author-email: rachael.skyner@diamond.ac.uk
License: Apache 2.0
Platform: UNKNOWN
Classifier: Development Status :: 4 - Beta
Classifier: Intended Audience :: Developers
Classifier: Topic :: Software Development :: Build Tools
Classifier: License :: OSI Approved :: Apache Software License
Classifier: Programming Language :: Python :: 3.6
Requires-Dist: django
Requires-Dist: psycopg2-binary
Requires-Dist: django-extensions
Requires-Dist: django-mysql
Requires-Dist: mysql-connector-python
Requires-Dist: pygraphviz
Provides-Extra: dev
Requires-Dist: check-manifest ; extra == 'dev'
Provides-Extra: test
Requires-Dist: coverage ; extra == 'test'
